vkstatusimage/__main__.py
vkstatusimage/api.py
vkstatusimage/oauth.py
vkstatusimage-1.0.0.dist-info/METADATA
vkstatusimage-1.0.0.dist-info/WHEEL
vkstatusimage-1.0.0.dist-info/entry_points.txt
vkstatusimage-1.0.0.dist-info/top_level.txt
vkstatusimage-1.0.0.dist-info/RECORD
