Metadata-Version: 2.1
Name: vkstatusimage
Version: 1.0.0
Summary: Tool for changing status images in VK.
Author-email: Vadim Grebenyuk <gemgameru@mail.ru>
Project-URL: Homepage, https://github.com/gemgameru/vkstatusimage
Project-URL: Bug Tracker, https://github.com/gemgameru/vkstatusimage/issues
Classifier: Programming Language :: Python :: 3
Classifier: Environment :: Console
Classifier: Operating System :: OS Independent
Classifier: Intended Audience :: Customer Service
Requires-Python: >=3.10
Provides-Extra: dev
Requires-Dist: black ; extra == 'dev'
